safrs/__about__.py
safrs/__init__.py
safrs/_safrs_relationship.py
safrs/api_methods.py
safrs/attr_parse.py
safrs/base.py
safrs/config.py
safrs/errors.py
safrs/jabase.py
safrs/json_encoder.py
safrs/jsonapi.py
safrs/jsonapi_attr.py
safrs/jsonapi_filters.py
safrs/jsonapi_formatting.py
safrs/request.py
safrs/response.py
safrs/safrs_api.py
safrs/safrs_init.py
safrs/safrs_types.py
safrs/swagger_doc.py
safrs/util.py
safrs-3.1.7.dist-info/licenses/LICENSE
safrs-3.1.7.dist-info/METADATA
safrs-3.1.7.dist-info/WHEEL
safrs-3.1.7.dist-info/top_level.txt
safrs-3.1.7.dist-info/RECORD
