Metadata-Version: 2.4
Name: safrs
Version: 3.1.7
Summary: SAFRS : SqlAlchemy Flask-Restful Swagger
Home-page: https://github.com/thomaxxl/safrs
Download-URL: https://github.com/thomaxxl/safrs/archive/3.1.7.tar.gz
Author: Thomas Pollet
Author-email: Thomas Pollet <thomas.pollet@gmail.com>
License:                     GNU GENERAL PUBLIC LICENSE
Project-URL: Homepage, https://github.com/thomaxxl/safrs
Keywords: SqlAlchemy,Flask,REST,Swagger,JsonAPI,OpenAPI
Classifier: Development Status :: 3 - Alpha
Classifier: Intended Audience :: Developers
Classifier: Topic :: Software Development :: Libraries
Classifier: Framework :: Flask
Classifier: License :: OSI Approved :: GNU General Public License v3 (GPLv3)
Classifier: Programming Language :: Python :: 3
Classifier: Programming Language :: Python :: 3.7
Classifier: Programming Language :: Python :: 3.8
Classifier: Programming Language :: Python :: 3.9
Classifier: Programming Language :: Python :: 3.10
Classifier: Programming Language :: Python :: 3.11
Classifier: Programming Language :: Python :: 3 :: Only
Requires-Python: >=3.6, !=3.0.*, !=3.1.*, !=3.2.*, <4
License-File: LICENSE
Requires-Dist: Flask-SQLAlchemy>=3.0.3
Requires-Dist: flask_swagger_ui>=4.11.1
Requires-Dist: flask-restful-swagger-2>=0.35
Requires-Dist: PyYaml>=6.0
Provides-Extra: dev
Requires-Dist: flask_cors; extra == "dev"
Provides-Extra: test
Requires-Dist: flask_cors; extra == "test"
Dynamic: author
Dynamic: download-url
Dynamic: home-page
Dynamic: license-file
Dynamic: requires-python
